{ "17441": {
"version": "1", 
 "levelnames" : {
      "001": "VANILLA SECRET 2",
      "002": "VANILLA SECRET 3",
      "003": "TOP SECRET AREA",
      "004": "DONUT GHOST HOUSE",
      "005": "DONUT PLAINS 3",
      "006": "DONUT PLAINS 4",
      "007": "#2 MORTON'S CASTLE",
      "008": "GREEN SWITCH PALAC",
      "009": "DONUT PLAINS 2",
      "00A": "DONUT SECRET 1",
      "00B": "VANILLA FORTRESS",
      "00C": "BUTTER BRIDGE 1",
      "00D": "BUTTER BRIDGE 2",
      "00E": "#4 LUDWIG'S CASTLE",
      "00F": "CHEESE BRIDGE AREA",
      "010": "COOKIE MOUNTAIN",
      "011": "SODA LAKE",
      "012": "STAR ROAD",
      "013": "DONUT SECRET HOUSE",
      "014": "YELOW SWITCH PALAC",
      "015": "-",
      "016": "-",
      "017": "-",
      "018": "-",
      "019": "-",
      "01A": "-",
      "01B": "-",
      "01C": "-",
      "01D": "-",
      "01E": "-",
      "01F": "-",
      "020": "-",
      "021": "-",
      "022": "-",
      "023": "-",
      "024": "-",
      "101": "CHUCK CITY",
      "102": "TERMINAL VELOCITY",
      "103": "EVERYTHING IS FINE",
      "104": "-",
      "105": "GOOMBA JAM",
      "106": "RUN FOREST",
      "107": "COLOR CODE COVE",
      "108": "LINKDEAD SHED",
      "109": "GLITCHCAT LAKE",
      "10A": "YELLOW DWARF",
      "10B": "INFERNO",
      "10C": "SAWRFING CASTLE",
      "10D": "TOWER OF POWER",
      "10E": "RAINBOW ROAD",
      "10F": "BARB'S SHIPHOLE",
      "110": "WHITE MOTH LAIR",
      "111": "-",
      "112": "-",
      "113": "-",
      "114": "-",
      "115": "-",
      "116": "-",
      "117": "-",
      "118": "-",
      "119": "-",
      "11A": "-",
      "11B": "-",
      "11C": "-",
      "11D": "-",
      "11E": "-",
      "11F": "-",
      "120": "-",
      "121": "-",
      "122": "-",
      "123": "-",
      "124": "-",
      "125": "-",
      "126": "-",
      "127": "-",
      "128": "-",
      "129": "-",
      "12A": "-",
      "12B": "-",
      "12C": "-",
      "12D": "-",
      "12E": "-",
      "12F": "-",
      "130": "-",
      "131": "-",
      "132": "-",
      "133": "-",
      "134": "-",
      "135": "-",
      "136": "SPECIAL WORLD",
      "137": "QUICKIE WORLD",
      "138": "-",
      "139": "",
      "13A": "",
      "13B": ""
}
}}

